type_infer/__init__.py
type_infer/api.py
type_infer/base.py
type_infer/bert/__init__.py
type_infer/bert/core.py
type_infer/dtype.py
type_infer/helpers.py
type_infer/rule_based/__init__.py
type_infer/rule_based/core.py
type_infer/rule_based/helpers.py
type_infer-0.0.25.dist-info/LICENSE
type_infer-0.0.25.dist-info/METADATA
type_infer-0.0.25.dist-info/WHEEL
type_infer-0.0.25.dist-info/RECORD
