Metadata-Version: 2.3
Name: type_infer
Version: 0.0.25
Summary: Automated type inference for Machine Learning pipelines.
License: GPL-3.0
Author: MindsDB Inc.
Author-email: hello@mindsdb.com
Requires-Python: >=3.10,<3.14
Classifier: License :: OSI Approved :: GNU General Public License v3 (GPLv3)
Classifier: Programming Language :: Python :: 3
Classifier: Programming Language :: Python :: 3.10
Classifier: Programming Language :: Python :: 3.11
Classifier: Programming Language :: Python :: 3.12
Classifier: Programming Language :: Python :: 3.13
Requires-Dist: colorlog (>=6.5.0,<7.0.0)
Requires-Dist: dataclasses-json (>=0.6.3,<0.7.0)
Requires-Dist: nltk (>=3.9,<4.0)
Requires-Dist: numpy (>=1.26,<2.0)
Requires-Dist: pandas (>=2,<3)
Requires-Dist: psutil (>=7.0,<8.0)
Requires-Dist: py3langid (>=0.2.2,<0.3)
Requires-Dist: python-dateutil (>=2.1,<3.0)
Requires-Dist: scipy (>=1,<2)
Requires-Dist: standard-imghdr (>=3.13,<4.0)
Requires-Dist: standard-sndhdr (>=3.13,<4.0)
Requires-Dist: toml (>=0.10.2,<0.11.0)
